boris/__init__.py
boris/_version.py
boris/admin.py
boris/app_settings.py
boris/apps.py
boris/models.py
boris/serializers.py
boris/tasks.py
boris/tests.py
boris/migrations/0001_initial.py
boris/migrations/0002_auto_20181119_2210.py
boris/migrations/__init__.py
boris/spiders/__init__.py
boris/spiders/base.py
boris/spiders/exceptions.py
boris/spiders/mercury.py
boris/spiders/readability.py
test_boris_project/__init__.py
test_boris_project/manage.py
test_boris_project/settings.py
test_boris_project/urls.py
django_boris-0.1.0.dist-info/LICENSE.txt
django_boris-0.1.0.dist-info/METADATA
django_boris-0.1.0.dist-info/WHEEL
django_boris-0.1.0.dist-info/top_level.txt
django_boris-0.1.0.dist-info/RECORD
