Metadata-Version: 2.1
Name: django-boris
Version: 0.1.0
Summary: UNKNOWN
Home-page: https://bitbucket.org/lullis/django_boris
Author: UNKNOWN
Author-email: UNKNOWN
License: UNKNOWN
Keywords: django crawling content_extraction readability
Platform: UNKNOWN
Classifier: Environment :: Web Environment
Classifier: Framework :: Django
Classifier: Operating System :: POSIX :: Linux
Classifier: Programming Language :: Python
Classifier: Programming Language :: Python :: 3.5
Classifier: Programming Language :: Python :: 3.6
Classifier: Topic :: Internet :: WWW/HTTP
Classifier: Topic :: Internet :: WWW/HTTP :: Dynamic Content
Requires-Dist: beautifulsoup4
Requires-Dist: celery
Requires-Dist: django (>=2.0)
Requires-Dist: django-model-utils
Requires-Dist: filemagic (==1.6)
Requires-Dist: html-sanitizer
Requires-Dist: mercury-parserpy
Requires-Dist: pillow
Requires-Dist: psycopg2-binary
Requires-Dist: readability-lxml
Requires-Dist: requests
